filters/__init__.py
filters/filters.py
filters/middleware.py
django_filters_clone-0.2.1.dist-info/AUTHORS
django_filters_clone-0.2.1.dist-info/LICENSE
django_filters_clone-0.2.1.dist-info/METADATA
django_filters_clone-0.2.1.dist-info/WHEEL
django_filters_clone-0.2.1.dist-info/top_level.txt
django_filters_clone-0.2.1.dist-info/RECORD
