Metadata-Version: 2.1
Name: django-filters-clone
Version: 0.2.1
Summary: A filterset and filters
Home-page: http://github.com/baskoopmans/django-filters/
Author: Bas Koopmans
Author-email: django@baskoopmans.nl
License: BSD
Download-URL: http://github.com/baskoopmans/django-filters/downloads
Platform: UNKNOWN
Classifier: Development Status :: 4 - Beta
Classifier: Environment :: Web Environment
Classifier: Framework :: Django
Classifier: Intended Audience :: Developers
Classifier: License :: OSI Approved :: BSD License
Classifier: Operating System :: OS Independent
Classifier: Programming Language :: Python
Classifier: Topic :: Software Development :: Libraries :: Python Modules
